[
  {
    "id": "system_0",
    "name": "top_system",
    "bus": [
      {
        "type": "bus",
        "masterIDs": [
          "cpu_0"
        ],
        "slaveIDs": [
          "mem_0"
        ],
        "id": "bus_0",
        "name": "top_bus"
      }
    ],
    "memories": [
      {
        "type": "memory",
        "id": "mem_0",
        "name": "top_ddr",
        "slaveLocates": [
          {
            "start": "0x80000000",
            "end": "0xFFFFFFFF"
          }
        ]
      }
    ],
    "devices": [],
    "cpu": {
      "type": "cpu",
      "id": "cpu_0",
      "name": "top_cpu",
      "masterViews": {
        "busID": "bus_0",
        "addressViews": [
          {
            "start": "0x00000000",
            "end": "0xFFFFFFFF"
          }
        ]
      }
    }
  },
  {
    "id": "system_1",
    "name": "sub_system_1",
    "bus": [
      {
        "type": "bus",
        "masterIDs": [
          "cpu_1",
          "dev_0",
          "dev_1"
        ],
        "slaveIDs": [
          "mem_1",
          "mem_2",
          "mem_5",
          "dev_0",
          "dev_1"
        ],
        "id": "bus_1",
        "name": "s1_bus"
      }
    ],
    "memories": [
      {
        "type": "memory",
        "id": "mem_1",
        "name": "s1_buf_a",
        "slaveLocates": [
          {
            "start": "0x00000000",
            "end": "0x000FFFFF"
          }
        ]
      },
      {
        "type": "memory",
        "id": "mem_2",
        "name": "s1_buf_b",
        "slaveLocates": [
          {
            "start": "0x00100000",
            "end": "0x001FFFFF"
          }
        ]
      },
      {
        "type": "memory",
        "id": "mem_5",
        "name": "s1_ddr",
        "slaveLocates": [
          {
            "start": "0xC0000000",
            "end": "0xFFFFFFFF"
          }
        ]
      }
    ],
    "devices": [
      {
        "type": "device",
        "slaveLocates": [
          {
            "start": "0x00A00000",
            "end": "0x00A03FFF"
          }
        ],
        "id": "dev_0",
        "name": "s1_eng_1_a",
        "masterViews": {
          "busID": "bus_1",
          "addressViews": [
            {
              "start": "0x000FFFFF",
              "end": "0x001FFFFF"
            },
            {
              "start": "0xC0000000",
              "end": "0xFFFFFFFF"
            }
          ]
        }
      },
      {
        "type": "device",
        "slaveLocates": [
          {
            "start": "0x00A04000",
            "end": "0x00A07FFF"
          }
        ],
        "id": "dev_1",
        "name": "s1_eng_2_a",
        "masterViews": {
          "busID": "bus_1",
          "addressViews": [
            {
              "start": "0x000FFFFF",
              "end": "0x001FFFFF"
            }
          ]
        }
      }
    ],
    "cpu": {
      "type": "cpu",
      "id": "cpu_1",
      "name": "s1_cpu",
      "masterViews": {
        "busID": "bus_1",
        "addressViews": [
          {
            "start": "0x00000000",
            "end": "0xFFFFFFFF"
          }
        ]
      }
    }
  },
  {
    "id": "system_2",
    "name": "sub_system_2",
    "bus": [
      {
        "type": "bus",
        "masterIDs": [
          "cpu_2",
          "dev_0",
          "dev_1"
        ],
        "slaveIDs": [
          "mem_6",
          "mem_7",
          "mem_10",
          "dev_0",
          "dev_1"
        ],
        "id": "bus_2",
        "name": "s2_bus"
      }
    ],
    "memories": [
      {
        "type": "memory",
        "id": "mem_6",
        "name": "s2_buf_a",
        "slaveLocates": [
          {
            "start": "0x00000000",
            "end": "0x000FFFFF"
          }
        ]
      },
      {
        "type": "memory",
        "id": "mem_7",
        "name": "s2_buf_b",
        "slaveLocates": [
          {
            "start": "0x00100000",
            "end": "0x001FFFFF"
          }
        ]
      },
      {
        "type": "memory",
        "id": "mem_10",
        "name": "s2_ddr",
        "slaveLocates": [
          {
            "start": "0xC0000000",
            "end": "0xFFFFFFFF"
          }
        ]
      }
    ],
    "devices": [
      {
        "type": "device",
        "slaveLocates": [
          {
            "start": "0x00A00000",
            "end": "0x00A03FFF"
          }
        ],
        "id": "dev_0",
        "name": "s1_eng_1_a",
        "masterViews": {
          "busID": "bus_2",
          "addressViews": [
            {
              "start": "0x000FFFFF",
              "end": "0x001FFFFF"
            },
            {
              "start": "0xC0000000",
              "end": "0xFFFFFFFF"
            }
          ]
        }
      },
      {
        "type": "device",
        "slaveLocates": [
          {
            "start": "0x00A04000",
            "end": "0x00A07FFF"
          }
        ],
        "id": "dev_1",
        "name": "s1_eng_2_a",
        "masterViews": {
          "busID": "bus_2",
          "addressViews": [
            {
              "start": "0x000FFFFF",
              "end": "0x001FFFFF"
            }
          ]
        }
      }
    ],
    "cpu": {
      "type": "cpu",
      "id": "cpu_2",
      "name": "s2_cpu",
      "masterViews": {
        "busID": "bus_2",
        "addressViews": [
          {
            "start": "0x00000000",
            "end": "0xFFFFFFFF"
          }
        ]
      }
    }
  }
]
